README
ez_setup.py
setup.py
pygnet/__init__.py
pygnet/client.py
pygnet/protocol.py
pygnet/server.py
pygnet.egg-info/PKG-INFO
pygnet.egg-info/SOURCES.txt
pygnet.egg-info/dependency_links.txt
pygnet.egg-info/requires.txt
pygnet.egg-info/top_level.txt
tests/client.py
tests/server.py
