Metadata-Version: 1.0
Name: pygnet
Version: 5
Summary: pygnet is a minimal layer on top of Twisted, for pygame.
Home-page: http://code.google.com/p/pygnet/
Author: Simon Wittber
Author-email: simonwittber@gmail.com
License: MIT
Platform: Any
